AUTHORS.rst
CONTRIBUTING.rst
HISTORY.rst
LICENSE
MANIFEST.in
README.rst
setup.cfg
setup.py
docs/Makefile
docs/authors.rst
docs/code.rst
docs/conf.py
docs/contributing.rst
docs/history.rst
docs/index.rst
docs/installation.rst
docs/make.bat
docs/modules.rst
docs/readme.rst
docs/usage.rst
docs/_build/html/_static/ajax-loader.gif
docs/_build/html/_static/comment-bright.png
docs/_build/html/_static/comment-close.png
docs/_build/html/_static/comment.png
docs/_build/html/_static/down-pressed.png
docs/_build/html/_static/down.png
docs/_build/html/_static/file.png
docs/_build/html/_static/minus.png
docs/_build/html/_static/plus.png
docs/_build/html/_static/up-pressed.png
docs/_build/html/_static/up.png
steel_toolbox/__init__.py
steel_toolbox/abq_tools.py
steel_toolbox/analytic_geometry.py
steel_toolbox/cli.py
steel_toolbox/lab_tests.py
steel_toolbox/parametric.py
steel_toolbox/polygonal.py
steel_toolbox/scan_3D.py
steel_toolbox/steel_design.py
steeltoolbox.egg-info/PKG-INFO
steeltoolbox.egg-info/SOURCES.txt
steeltoolbox.egg-info/dependency_links.txt
steeltoolbox.egg-info/entry_points.txt
steeltoolbox.egg-info/not-zip-safe
steeltoolbox.egg-info/requires.txt
steeltoolbox.egg-info/top_level.txt
tests/__init__.py
tests/test_steel_toolbox.py
tests/test_data/edge_01.pkl
tests/test_data/edge_02.pkl
tests/test_data/edge_03.pkl
tests/test_data/edge_04.pkl
tests/test_data/edge_05.pkl
tests/test_data/edge_06.pkl
tests/test_data/edge_07.pkl
tests/test_data/edge_08.pkl
tests/test_data/edge_09.pkl
tests/test_data/edge_10.pkl
tests/test_data/edge_11.pkl
tests/test_data/edge_12.pkl
tests/test_data/edge_13.pkl
tests/test_data/edge_14.pkl
tests/test_data/edge_15.pkl
tests/test_data/edge_16.pkl
tests/test_data/side_01.pkl
tests/test_data/side_02.pkl
tests/test_data/side_03.pkl
tests/test_data/side_04.pkl
tests/test_data/side_05.pkl
tests/test_data/side_06.pkl
tests/test_data/side_07.pkl
tests/test_data/side_08.pkl
tests/test_data/side_09.pkl
tests/test_data/side_10.pkl
tests/test_data/side_11.pkl
tests/test_data/side_12.pkl
tests/test_data/side_13.pkl
tests/test_data/side_14.pkl
tests/test_data/side_15.pkl
tests/test_data/side_16.pkl
tests/test_data/experiment/init_sample_1.asc
tests/test_data/experiment/init_sample_1.bin
