Metadata-Version: 1.1
Name: steeltoolbox
Version: 0.3.0
Summary: A collection of classes and tools used on structural steel research and design.
Home-page: https://github.com/manpan-1/steel_toolbox
Author: Panagiotis Manoleas
Author-email: manpan@ltu.se
License: MIT license
Keywords: steel_toolbox
Platform: UNKNOWN
Classifier: Development Status :: 5 - Production/Stable
Classifier: Intended Audience :: Science/Research
Classifier: License :: OSI Approved :: MIT License
Classifier: Natural Language :: English
Classifier: Programming Language :: Python :: 3.5
